{"listSentences":[{"id":34373,"recordId":1.40831122805967008E17,"content":"Xuất_hiện đột_ngột trưa nay với ngất , không nhận_biết người_thân ( theo lời Ông chồng khai ) , ghi_nhận HA tại nhà lần một 170 / ? và lần hai không đo được .","section":"TK_BENHLY","concept":[{"content":"không nhận_biết người_thân","type":"PR","sentenceId":34373,"recordId":1.40831122805967008E17,"fromWord":8,"toWord":10,"fromChar":39,"toChar":65},{"content":"HA tại nhà lần một 170","type":"TE","sentenceId":34373,"recordId":1.40831122805967008E17,"fromWord":20,"toWord":25,"fromChar":105,"toChar":127}],"handle":1},{"id":34375,"recordId":1.40831122805967008E17,"content":"Bệnh_nhân được đưa vào cấp_cứu BV Vũ_Anh HA 170/90mmHg và được chuyển lên khoa_nội điều_trị - - - > Sau điều_trị BN ổn - - - > XV .","section":"TK_BENHLY","concept":[{"content":"HA","type":"TE","sentenceId":34375,"recordId":1.40831122805967008E17,"fromWord":8,"toWord":8,"fromChar":41,"toChar":43}],"handle":1}]}