{"listSentences":[{"id":22913,"recordId":1.40621055533604E17,"content":"Phẫu_thuật","section":"DIEUTRI","concept":[{"content":"Phẫu_thuật","type":"TR","sentenceId":22913,"recordId":1.40621055533604E17,"fromWord":1,"toWord":1,"fromChar":0,"toChar":10}],"handle":1},{"id":22914,"recordId":1.40621055533604E17,"content":"Bệnh_nhân nữ 38 tuổi , được chẩn_đoán : Nhân giáp thùy ( P ) .","section":"KB_TOMTAT","concept":[{"content":"Nhân giáp thùy ( P )","type":"PR","sentenceId":22914,"recordId":1.40621055533604E17,"fromWord":9,"toWord":14,"fromChar":40,"toChar":60}],"handle":1},{"id":22919,"recordId":1.40621055533604E17,"content":"Phẫu_thuật","section":"TK_PHUONGPHAP","concept":[{"content":"Phẫu_thuật","type":"TR","sentenceId":22919,"recordId":1.40621055533604E17,"fromWord":1,"toWord":1,"fromChar":0,"toChar":10}],"handle":1}]}