{"listSentences":[{"id":20295,"recordId":1.40605105229004992E17,"content":"Bệnh 4 ngày_nay , BN sốt cao liện tục , kèm theo đau họng , ho_khan , nhức đầu , chóng_mặt , ăn_uống kém , nôn ói thức_ăn sau ăn .","section":"TK_BENHLY","concept":[{"content":"sốt cao liện tục","type":"PR","sentenceId":20295,"recordId":1.40605105229004992E17,"fromWord":6,"toWord":9,"fromChar":21,"toChar":37},{"content":"đau họng","type":"PR","sentenceId":20295,"recordId":1.40605105229004992E17,"fromWord":13,"toWord":14,"fromChar":49,"toChar":57},{"content":"ho_khan","type":"PR","sentenceId":20295,"recordId":1.40605105229004992E17,"fromWord":16,"toWord":16,"fromChar":60,"toChar":67},{"content":"nhức đầu","type":"PR","sentenceId":20295,"recordId":1.40605105229004992E17,"fromWord":18,"toWord":19,"fromChar":70,"toChar":78},{"content":"chóng_mặt","type":"PR","sentenceId":20295,"recordId":1.40605105229004992E17,"fromWord":21,"toWord":21,"fromChar":81,"toChar":90},{"content":"ăn_uống kém","type":"PR","sentenceId":20295,"recordId":1.40605105229004992E17,"fromWord":23,"toWord":24,"fromChar":93,"toChar":104},{"content":"nôn ói thức_ăn sau ăn","type":"PR","sentenceId":20295,"recordId":1.40605105229004992E17,"fromWord":26,"toWord":30,"fromChar":107,"toChar":128}],"handle":1},{"id":20297,"recordId":1.40605105229004992E17,"content":"BN điều_trị không giảm khám nhập_viện .","section":"TK_BENHLY","concept":[{"content":"điều_trị","type":"TR","sentenceId":20297,"recordId":1.40605105229004992E17,"fromWord":2,"toWord":2,"fromChar":3,"toChar":11}],"handle":1},{"id":20299,"recordId":1.40605105229004992E17,"content":"Sau điều_trị bệnh ổn cho xuất_viện","section":"TK_BENHLY","concept":[{"content":"điều_trị","type":"TR","sentenceId":20299,"recordId":1.40605105229004992E17,"fromWord":2,"toWord":2,"fromChar":4,"toChar":12}],"handle":1},{"id":20301,"recordId":1.40605105229004992E17,"content":"Kháng_sinh","section":"TK_PHUONGPHAP","concept":[{"content":"Kháng_sinh","type":"TR","sentenceId":20301,"recordId":1.40605105229004992E17,"fromWord":1,"toWord":1,"fromChar":0,"toChar":10}],"handle":1}]}