{"listSentences":[{"id":23714,"recordId":1.40626083306924E17,"content":"Ho khò_khè","section":"LYDO","concept":[{"content":"Ho khò_khè","type":"PR","sentenceId":23714,"recordId":1.40626083306924E17,"fromWord":1,"toWord":2,"fromChar":0,"toChar":10}],"handle":1},{"id":23715,"recordId":1.40626083306924E17,"content":"cháu ho khò_khè 2 tuần nay , khám uống thuốc viêm mũi họng nhưng bệnh không giảm , từ hôm_qua đến giờ cháu ho nhiều , thở khò_khè , ăn_uống kém , tiêu phân lỏng 4 ngày_nay , người mệt nhiều","section":"HB_BENHLY","concept":[{"content":"ho khò_khè","type":"PR","sentenceId":23715,"recordId":1.40626083306924E17,"fromWord":2,"toWord":3,"fromChar":5,"toChar":15},{"content":"khám uống thuốc viêm mũi họng","type":"TR","sentenceId":23715,"recordId":1.40626083306924E17,"fromWord":8,"toWord":13,"fromChar":29,"toChar":58},{"content":"ho nhiều","type":"PR","sentenceId":23715,"recordId":1.40626083306924E17,"fromWord":24,"toWord":25,"fromChar":107,"toChar":115},{"content":"thở khò_khè","type":"PR","sentenceId":23715,"recordId":1.40626083306924E17,"fromWord":27,"toWord":28,"fromChar":118,"toChar":129},{"content":"ăn_uống kém","type":"PR","sentenceId":23715,"recordId":1.40626083306924E17,"fromWord":30,"toWord":31,"fromChar":132,"toChar":143},{"content":"tiêu phân lỏng 4 ngày_nay","type":"PR","sentenceId":23715,"recordId":1.40626083306924E17,"fromWord":33,"toWord":37,"fromChar":146,"toChar":171},{"content":"người mệt nhiều","type":"PR","sentenceId":23715,"recordId":1.40626083306924E17,"fromWord":39,"toWord":41,"fromChar":174,"toChar":189}],"handle":1},{"id":23716,"recordId":1.40626083306924E17,"content":"khỏe","section":"HB_BANTHAN","concept":[],"handle":1},{"id":23727,"recordId":1.40626083306924E17,"content":"kháng_sinh , kháng_viêm , men vi_sinh , giản phế_quản , giảm ho","section":"DIEUTRI","concept":[{"content":"kháng_sinh","type":"TR","sentenceId":23727,"recordId":1.40626083306924E17,"fromWord":1,"toWord":1,"fromChar":0,"toChar":10},{"content":"kháng_viêm","type":"TR","sentenceId":23727,"recordId":1.40626083306924E17,"fromWord":3,"toWord":3,"fromChar":13,"toChar":23},{"content":"men vi_sinh","type":"TR","sentenceId":23727,"recordId":1.40626083306924E17,"fromWord":5,"toWord":6,"fromChar":26,"toChar":37},{"content":"giản phế_quản","type":"TR","sentenceId":23727,"recordId":1.40626083306924E17,"fromWord":8,"toWord":9,"fromChar":40,"toChar":53},{"content":"giảm ho","type":"TR","sentenceId":23727,"recordId":1.40626083306924E17,"fromWord":11,"toWord":12,"fromChar":56,"toChar":63}],"handle":1}]}