{"listSentences":[{"id":21839,"recordId":1.40616101037366E17,"content":"Bệnh vài ngày_nay , BN đau_đầu nhiều , sốt ớn lạnh , kèm theo nhức mỏi toàn_thân , ăn_uống kém , mệt chóng váng khi đi_lại .","section":"TK_BENHLY","concept":[{"content":"đau_đầu nhiều","type":"PR","sentenceId":21839,"recordId":1.40616101037366E17,"fromWord":6,"toWord":7,"fromChar":23,"toChar":36},{"content":"sốt ớn lạnh","type":"PR","sentenceId":21839,"recordId":1.40616101037366E17,"fromWord":9,"toWord":11,"fromChar":39,"toChar":50},{"content":"nhức mỏi toàn_thân","type":"PR","sentenceId":21839,"recordId":1.40616101037366E17,"fromWord":15,"toWord":17,"fromChar":62,"toChar":80},{"content":"ăn_uống kém","type":"PR","sentenceId":21839,"recordId":1.40616101037366E17,"fromWord":19,"toWord":20,"fromChar":83,"toChar":94},{"content":"mệt chóng váng khi đi_lại","type":"PR","sentenceId":21839,"recordId":1.40616101037366E17,"fromWord":22,"toWord":26,"fromChar":97,"toChar":122}],"handle":1},{"id":21841,"recordId":1.40616101037366E17,"content":"BN điều_trị không giảm khám nhập_viện .","section":"TK_BENHLY","concept":[{"content":"điều_trị","type":"TR","sentenceId":21841,"recordId":1.40616101037366E17,"fromWord":2,"toWord":2,"fromChar":3,"toChar":11}],"handle":1},{"id":21843,"recordId":1.40616101037366E17,"content":"Sau điều_trị bệnh giảm cho xuất_viện","section":"TK_BENHLY","concept":[{"content":"điều_trị","type":"TR","sentenceId":21843,"recordId":1.40616101037366E17,"fromWord":2,"toWord":2,"fromChar":4,"toChar":12}],"handle":1}]}