{"listSentences":[{"id":5080,"recordId":1.40220185445288992E17,"content":"Bệnh khoảng tuần nay , BN ho đàm khó khạc , kèm theo tức ngực khi ho , sốt cao liên_tục , đau_đầu , ăn_uống kém .","section":"TK_BENHLY","concept":[{"content":"ho đàm khó khạc","type":"PR","sentenceId":5080,"recordId":1.40220185445288992E17,"fromWord":7,"toWord":10,"fromChar":26,"toChar":41},{"content":"tức ngực khi ho","type":"PR","sentenceId":5080,"recordId":1.40220185445288992E17,"fromWord":14,"toWord":17,"fromChar":53,"toChar":68},{"content":"sốt cao liên_tục","type":"PR","sentenceId":5080,"recordId":1.40220185445288992E17,"fromWord":19,"toWord":21,"fromChar":71,"toChar":87},{"content":"đau_đầu","type":"PR","sentenceId":5080,"recordId":1.40220185445288992E17,"fromWord":23,"toWord":23,"fromChar":90,"toChar":97},{"content":"ăn_uống kém","type":"PR","sentenceId":5080,"recordId":1.40220185445288992E17,"fromWord":25,"toWord":26,"fromChar":100,"toChar":111}],"handle":1},{"id":5082,"recordId":1.40220185445288992E17,"content":"BN tự mua thuốc uống không giảm khám nhập_viện .","section":"TK_BENHLY","concept":[{"content":"mua thuốc uống","type":"TR","sentenceId":5082,"recordId":1.40220185445288992E17,"fromWord":3,"toWord":5,"fromChar":6,"toChar":20}],"handle":1},{"id":5084,"recordId":1.40220185445288992E17,"content":"Sau đều trị bệnh ổn cho xuất_viện","section":"TK_BENHLY","concept":[{"content":"đều trị","type":"TR","sentenceId":5084,"recordId":1.40220185445288992E17,"fromWord":2,"toWord":3,"fromChar":4,"toChar":11}],"handle":1}]}